openstack_virtual_baremetal/__init__.py
openstack_virtual_baremetal/auth.py
openstack_virtual_baremetal/build_nodes_json.py
openstack_virtual_baremetal/deploy.py
openstack_virtual_baremetal/openstackbmc.py
openstack_virtual_baremetal/tests/__init__.py
openstack_virtual_baremetal/tests/test_auth.py
openstack_virtual_baremetal/tests/test_build_nodes_json.py
openstack_virtual_baremetal/tests/test_deploy.py
openstack_virtual_baremetal/tests/test_openstackbmc.py
openstack_virtual_baremetal-1.0.2.dev28.dist-info/AUTHORS
openstack_virtual_baremetal-1.0.2.dev28.dist-info/METADATA
openstack_virtual_baremetal-1.0.2.dev28.dist-info/WHEEL
openstack_virtual_baremetal-1.0.2.dev28.dist-info/entry_points.txt
openstack_virtual_baremetal-1.0.2.dev28.dist-info/pbr.json
openstack_virtual_baremetal-1.0.2.dev28.dist-info/top_level.txt
openstack_virtual_baremetal-1.0.2.dev28.dist-info/RECORD
