Metadata-Version: 2.1
Name: openstack-virtual-baremetal
Version: 1.0.2.dev28
Summary: A collection of tools for using OpenStack instances to test baremetal deployment
Home-page: http://www.redhat.com/
Author: Ben Nemec
Author-email: bnemec@redhat.com
License: UNKNOWN
Platform: UNKNOWN
Classifier: Environment :: OpenStack
Classifier: Intended Audience :: Information Technology
Classifier: Intended Audience :: System Administrators
Classifier: License :: OSI Approved :: Apache Software License
Classifier: Operating System :: POSIX :: Linux
Classifier: Programming Language :: Python
Classifier: Programming Language :: Python :: 2
Classifier: Programming Language :: Python :: 2.7
Classifier: Programming Language :: Python :: 3
Classifier: Programming Language :: Python :: 3.4
Requires-Dist: os-client-config
Requires-Dist: pyghmi
Requires-Dist: PyYAML
Requires-Dist: python-glanceclient
Requires-Dist: python-heatclient
Requires-Dist: python-keystoneclient
Requires-Dist: python-neutronclient
Requires-Dist: python-novaclient
